README.md
setup.py
komora_syncer/__init__.py
komora_syncer/__main__.py
komora_syncer/config.py
komora_syncer.egg-info/PKG-INFO
komora_syncer.egg-info/SOURCES.txt
komora_syncer.egg-info/dependency_links.txt
komora_syncer.egg-info/entry_points.txt
komora_syncer.egg-info/not-zip-safe
komora_syncer.egg-info/requires.txt
komora_syncer.egg-info/top_level.txt
komora_syncer/connections/KomoraApi.py
komora_syncer/connections/KomoraConnection.py
komora_syncer/connections/NetboxConnection.py
komora_syncer/connections/__init__.py
komora_syncer/helpers/__init__.py
komora_syncer/helpers/utils.py
komora_syncer/models/__init__.py
komora_syncer/models/komora/__init__.py
komora_syncer/models/komora/address.py
komora_syncer/models/komora/contact.py
komora_syncer/models/komora/device.py
komora_syncer/models/komora/district.py
komora_syncer/models/komora/location.py
komora_syncer/models/komora/municipality.py
komora_syncer/models/komora/organization.py
komora_syncer/models/komora/region.py
komora_syncer/models/komora/site.py
komora_syncer/models/komora/site_contact.py
komora_syncer/models/netbox/NbDevice.py
komora_syncer/models/netbox/NbLocation.py
komora_syncer/models/netbox/NbProvider.py
komora_syncer/models/netbox/NbRegion.py
komora_syncer/models/netbox/NbSite.py
komora_syncer/models/netbox/NbTenant.py
komora_syncer/models/netbox/NetboxBase.py
komora_syncer/models/netbox/NetboxCache.py
komora_syncer/models/netbox/__init__.py
komora_syncer/processors/Synchronizer.py
komora_syncer/processors/__init__.py